[
  {
    "type": 0,
    "point": {
      "x": -666.0526,
      "y": 34.0177,
      "z": -1574.76282
    },
    "angle": 244.0
  },
  {
    "type": 0,
    "point": {
      "x": -711.2046,
      "y": 34.0333252,
      "z": -1536.77075
    },
    "angle": 180.0
  },
  {
    "type": 0,
    "point": {
      "x": 311.494873,
      "y": 64.128,
      "z": -1301.90381
    },
    "angle": 84.0
  },
  {
    "type": 0,
    "point": {
      "x": 347.152344,
      "y": 63.75389,
      "z": -1428.34021
    },
    "angle": 70.0
  },
  {
    "type": 0,
    "point": {
      "x": 722.5825,
      "y": 55.87995,
      "z": -1110.18542
    },
    "angle": 74.0
  },
  {
    "type": 0,
    "point": {
      "x": -759.9078,
      "y": 41.738472,
      "z": -1067.15942
    },
    "angle": 182.0
  },
  {
    "type": 0,
    "point": {
      "x": 143.785645,
      "y": 44.61991,
      "z": -880.373169
    },
    "angle": 0.0
  },
  {
    "type": 0,
    "point": {
      "x": 45.020752,
      "y": 44.61991,
      "z": -857.136353
    },
    "angle": 236.0
  },
  {
    "type": 1,
    "point": {
      "x": -1191.23755,
      "y": 57.5425758,
      "z": 820.4436
    },
    "angle": 134.0
  },
  {
    "type": 0,
    "point": {
      "x": -1130.282,
      "y": 58.04418,
      "z": 823.38446
    },
    "angle": 134.0
  },
  {
    "type": 2,
    "point": {
      "x": -1172.65552,
      "y": 57.54258,
      "z": 821.8203
    },
    "angle": 224.0
  },
  {
    "type": 0,
    "point": {
      "x": -328.985779,
      "y": 61.6620369,
      "z": 894.9974
    },
    "angle": 74.0
  },
  {
    "type": 5,
    "point": {
      "x": 1951.82422,
      "y": 177.002991,
      "z": 705.1714
    },
    "angle": 272.0
  },
  {
    "type": 0,
    "point": {
      "x": -871.484436,
      "y": 65.4057541,
      "z": 218.996338
    },
    "angle": 270.0
  },
  {
    "type": 0,
    "point": {
      "x": -907.94165,
      "y": 65.00345,
      "z": 136.422043
    },
    "angle": 0.0
  },
  {
    "type": 0,
    "point": {
      "x": -837.7754,
      "y": 32.49417,
      "z": -552.40564
    },
    "angle": 180.0
  },
  {
    "type": 0,
    "point": {
      "x": -756.0199,
      "y": 32.49417,
      "z": -424.9309
    },
    "angle": 180.0
  },
  {
    "type": 0,
    "point": {
      "x": -846.5094,
      "y": 32.49417,
      "z": -472.194458
    },
    "angle": 272.0
  },
  {
    "type": 4,
    "point": {
      "x": -1465.96692,
      "y": 67.24001,
      "z": 217.827286
    },
    "angle": 268.0
  },
  {
    "type": 4,
    "point": {
      "x": -1372.37036,
      "y": 72.55911,
      "z": 281.817383
    },
    "angle": 70.0
  },
  {
    "type": 4,
    "point": {
      "x": -1475.80835,
      "y": 66.71501,
      "z": 198.96875
    },
    "angle": 2.0
  },
  {
    "type": 1,
    "point": {
      "x": -237.807373,
      "y": 50.5265236,
      "z": -38.39673
    },
    "angle": 178.0
  },
  {
    "type": 0,
    "point": {
      "x": -285.429443,
      "y": 50.52652,
      "z": -64.91016
    },
    "angle": 88.0
  },
  {
    "type": 0,
    "point": {
      "x": 207.431763,
      "y": 55.03616,
      "z": 792.240234
    },
    "angle": 118.0
  },
  {
    "type": 7,
    "point": {
      "x": -537.1561,
      "y": 49.63584,
      "z": -1904.59546
    },
    "angle": 356.0
  },
  {
    "type": 7,
    "point": {
      "x": -750.696655,
      "y": 34.0020752,
      "z": -1612.42114
    },
    "angle": 356.0
  },
  {
    "type": 10,
    "point": {
      "x": -676.125,
      "y": 34.0214844,
      "z": -1602.41992
    },
    "angle": 356.0
  },
  {
    "type": 14,
    "point": {
      "x": -914.9359,
      "y": 19.4712753,
      "z": -1571.40979
    },
    "angle": 272.0
  },
  {
    "type": 14,
    "point": {
      "x": -914.960938,
      "y": 15.4730682,
      "z": -1124.81274
    },
    "angle": 256.0
  },
  {
    "type": 14,
    "point": {
      "x": -431.150757,
      "y": 21.9041386,
      "z": -524.4888
    },
    "angle": 256.0
  },
  {
    "type": 14,
    "point": {
      "x": 790.3374,
      "y": 22.9727459,
      "z": -1505.95081
    },
    "angle": 342.0
  },
  {
    "type": 16,
    "point": {
      "x": -236.555176,
      "y": 64.33987,
      "z": -1624.51343
    },
    "angle": 270.0
  },
  {
    "type": 7,
    "point": {
      "x": 129.688477,
      "y": 44.61991,
      "z": -779.7706
    },
    "angle": 256.0
  },
  {
    "type": 9,
    "point": {
      "x": 146.861084,
      "y": 44.61991,
      "z": -769.1942
    },
    "angle": 186.0
  },
  {
    "type": 9,
    "point": {
      "x": -823.8821,
      "y": 32.49417,
      "z": -495.420654
    },
    "angle": 182.0
  },
  {
    "type": 7,
    "point": {
      "x": -830.547241,
      "y": 32.49417,
      "z": -511.4297
    },
    "angle": 90.0
  },
  {
    "type": 14,
    "point": {
      "x": -944.178833,
      "y": 21.1268463,
      "z": -609.1658
    },
    "angle": 246.0
  },
  {
    "type": 12,
    "point": {
      "x": -756.3345,
      "y": 64.9268951,
      "z": 105.0791
    },
    "angle": 268.0
  },
  {
    "type": 13,
    "point": {
      "x": -742.026367,
      "y": 65.24146,
      "z": 229.6455
    },
    "angle": 268.0
  },
  {
    "type": 13,
    "point": {
      "x": -781.829468,
      "y": 64.9258347,
      "z": 59.9650879
    },
    "angle": 0.0
  },
  {
    "type": 10,
    "point": {
      "x": -806.630859,
      "y": 64.9401245,
      "z": 108.738281
    },
    "angle": 76.0
  },
  {
    "type": 2,
    "point": {
      "x": 801.5735,
      "y": 76.94519,
      "z": 1847.239
    },
    "angle": 184.0
  },
  {
    "type": 18,
    "point": {
      "x": 1341.86133,
      "y": 59.2364044,
      "z": 1358.17957
    },
    "angle": 270.0
  },
  {
    "type": 19,
    "point": {
      "x": 1342.18018,
      "y": 59.1785927,
      "z": 1394.83777
    },
    "angle": 268.0
  },
  {
    "type": 19,
    "point": {
      "x": 1268.96338,
      "y": 58.8778725,
      "z": 1537.18848
    },
    "angle": 268.0
  },
  {
    "type": 3,
    "point": {
      "x": 1179.50745,
      "y": 59.40527,
      "z": 1425.13281
    },
    "angle": 0.0
  },
  {
    "type": 3,
    "point": {
      "x": 1244.55786,
      "y": 58.8864059,
      "z": 1499.10571
    },
    "angle": 180.0
  },
  {
    "type": 8,
    "point": {
      "x": 989.3916,
      "y": 80.93462,
      "z": -49.965332
    },
    "angle": 180.0
  },
  {
    "type": 8,
    "point": {
      "x": 962.006,
      "y": 81.44472,
      "z": -66.35558
    },
    "angle": 0.0
  },
  {
    "type": 15,
    "point": {
      "x": 725.8721,
      "y": 60.0661659,
      "z": -734.9043
    },
    "angle": 0.0
  },
  {
    "type": 15,
    "point": {
      "x": 667.945068,
      "y": 60.0661659,
      "z": -777.7914
    },
    "angle": 220.0
  },
  {
    "type": 6,
    "point": {
      "x": 575.4646,
      "y": 80.21852,
      "z": -261.373535
    },
    "angle": 316.0
  },
  {
    "type": 6,
    "point": {
      "x": 556.8154,
      "y": 80.20802,
      "z": -244.4419
    },
    "angle": 90.0
  },
  {
    "type": 0,
    "point": {
      "x": 1396.07532,
      "y": 80.88148,
      "z": 331.283752
    },
    "angle": 224.0
  },
  {
    "type": 16,
    "point": {
      "x": 1359.89355,
      "y": 80.4111557,
      "z": 302.151367
    },
    "angle": 316.0
  },
  {
    "type": 1,
    "point": {
      "x": -510.953644,
      "y": 32.99003,
      "z": 1510.9093
    },
    "angle": 140.0
  },
  {
    "type": 8,
    "point": {
      "x": 726.9352,
      "y": 48.7361565,
      "z": 991.999
    },
    "angle": 90.0
  },
  {
    "type": 9,
    "point": {
      "x": 702.0788,
      "y": 48.7340469,
      "z": 847.8807
    },
    "angle": 58.0
  },
  {
    "type": 7,
    "point": {
      "x": 768.6629,
      "y": 48.7360535,
      "z": 744.2205
    },
    "angle": 0.0
  },
  {
    "type": 7,
    "point": {
      "x": 570.348,
      "y": 48.73616,
      "z": 832.5529
    },
    "angle": 84.0
  },
  {
    "type": 2,
    "point": {
      "x": 868.5254,
      "y": 48.7328568,
      "z": 901.2469
    },
    "angle": 296.0
  },
  {
    "type": 0,
    "point": {
      "x": 664.669,
      "y": 49.18423,
      "z": 1026.28979
    },
    "angle": 0.0
  },
  {
    "type": 0,
    "point": {
      "x": 682.608459,
      "y": 48.7361679,
      "z": 749.5596
    },
    "angle": 0.0
  },
  {
    "type": 0,
    "point": {
      "x": 850.545044,
      "y": 48.7361565,
      "z": 833.9194
    },
    "angle": 270.0
  },
  {
    "type": 0,
    "point": {
      "x": 802.584167,
      "y": 48.7361565,
      "z": 1019.90179
    },
    "angle": 0.0
  },
  {
    "type": 4,
    "point": {
      "x": 1640.22583,
      "y": 56.54406,
      "z": -1074.114
    },
    "angle": 42.0
  },
  {
    "type": 4,
    "point": {
      "x": 1440.74512,
      "y": 40.9556236,
      "z": -920.4248
    },
    "angle": 42.0
  },
  {
    "type": 17,
    "point": {
      "x": 1460.9082,
      "y": 10.0017853,
      "z": -1139.11792
    },
    "angle": 222.0
  },
  {
    "type": 18,
    "point": {
      "x": 1738.2959,
      "y": 56.369072,
      "z": -1092.28162
    },
    "angle": 314.0
  },
  {
    "type": 19,
    "point": {
      "x": 1720.66992,
      "y": 56.31906,
      "z": -1026.0354
    },
    "angle": 134.0
  },
  {
    "type": 4,
    "point": {
      "x": 1525.49414,
      "y": 40.9556236,
      "z": -900.256
    },
    "angle": 0.0
  },
  {
    "type": 1,
    "point": {
      "x": 1672.33179,
      "y": 162.392731,
      "z": -210.264648
    },
    "angle": 272.0
  },
  {
    "type": 18,
    "point": {
      "x": 1449.436,
      "y": 29.486639,
      "z": -1115.11609
    },
    "angle": 314.0
  },
  {
    "type": 17,
    "point": {
      "x": 1354.58008,
      "y": 15.0634136,
      "z": -990.000244
    },
    "angle": 314.0
  },
  {
    "type": 20,
    "point": {
      "x": 1532.81372,
      "y": 40.9556236,
      "z": -986.0665
    },
    "angle": 216.0
  },
  {
    "type": 20,
    "point": {
      "x": 1665.291,
      "y": 56.0239029,
      "z": -1108.97778
    },
    "angle": 104.0
  },
  {
    "type": 4,
    "point": {
      "x": 1528.06592,
      "y": 40.9556236,
      "z": -831.3948
    },
    "angle": 48.0
  },
  {
    "type": 3,
    "point": {
      "x": 1763.13867,
      "y": 56.019043,
      "z": -1057.00562
    },
    "angle": 264.0
  },
  {
    "type": 0,
    "point": {
      "x": 726.9553,
      "y": 48.7361565,
      "z": 896.2645
    },
    "angle": 270.0
  },
  {
    "type": 20,
    "point": {
      "x": 1250.74,
      "y": 58.8864059,
      "z": 1427.5564
    },
    "angle": 186.0
  },
  {
    "type": 2,
    "point": {
      "x": 1240.66553,
      "y": 59.4053,
      "z": 1564.50916
    },
    "angle": 0.0
  },
  {
    "type": 14,
    "point": {
      "x": -1459.16113,
      "y": 19.362896,
      "z": 818.7737
    },
    "angle": 0.0
  },
  {
    "type": 14,
    "point": {
      "x": -921.420532,
      "y": 17.2836666,
      "z": -1080.188
    },
    "angle": 254.0
  },
  {
    "type": 11,
    "point": {
      "x": 1015.05347,
      "y": 81.28463,
      "z": -38.8155327
    },
    "angle": 270.0
  },
  {
    "type": 2,
    "point": {
      "x": 373.119141,
      "y": 55.2533722,
      "z": 1572.46509
    },
    "angle": 38.0
  },
  {
    "type": 16,
    "point": {
      "x": -243.7378,
      "y": 60.1521072,
      "z": -1243.01355
    },
    "angle": 56.0
  },
  {
    "type": 0,
    "point": {
      "x": -221.79126,
      "y": 60.1521072,
      "z": -1219.12463
    },
    "angle": 180.0
  },
  {
    "type": 0,
    "point": {
      "x": 181.491943,
      "y": 56.76909,
      "z": -1778.03491
    },
    "angle": 306.0
  },
  {
    "type": 10,
    "point": {
      "x": -354.260132,
      "y": 61.12873,
      "z": 837.2737
    },
    "angle": 0.0
  }
]