{
  "name": "Fisherman_1",
  "path": "Servers/DataSerializing/Workshop/Steam/content/304930/1753131903/NPCs/Hawaii NPCs/Characters/Fisherman_1/Asset.dat",
  "data": {
    "GUID": "0fcfb97d090c4de3b8c667bfcc17cbce",
    "Type": "NPC",
    "ID": "2017",
    "Shirt": "510",
    "Pants": "511",
    "Hat": "509",
    "Hair": "19",
    "Face": "6",
    "Beard": "3",
    "Color_Skin": "#c7af8d",
    "Color_Hair": "#473928",
    "Tertiary": "503",
    "Equipped": "Tertiary",
    "Dialogue": "2018"
  },
  "translation": {
    "Name": "Fisherman John",
    "Character": "John"
  }
}