{
  "name": "Metro_Fish_Fish_Quest",
  "path": "Servers/DataSerializing/Workshop/Steam/content/304930/2136497468/Elver/Bundles/Main/Spawns/Metro_Fish_Fish_Quest/Metro_Fish_Fish_Quest.dat",
  "data": {
    "GUID": "220c643fb613422d8b95581566efa47d",
    "Type": "Spawn",
    "ID": "57148",
    "Tables": [
      {
        "LegacyAssetId": "57536",
        "Weight": "40"
      },
      {
        "LegacyAssetId": "57535",
        "Weight": "35"
      },
      {
        "LegacyAssetId": "57534",
        "Weight": "30"
      }
    ]
  },
  "translation": null
}