{
  "name": "Nitro_Welcome",
  "path": "Servers/DataSerializing/Workshop/Steam/content/304930/1753131903/NPCs/Hawaii NPCs/Dialogues/Ensign_Nitro/Nitro_Welcome/Asset.dat",
  "data": {
    "GUID": "29681fe77492420b8b46ac8ea1a9ad12",
    "Type": "Dialogue",
    "ID": "45713",
    "Messages": "2",
    "Message_0_Pages": "1",
    "Message_0_Responses": "1",
    "Message_0_Response_0": "0",
    "Message_0_Conditions": "1",
    "Message_0_Condition_0_Type": "Flag_Bool",
    "Message_0_Condition_0_ID": "45701",
    "Message_0_Condition_0_Value": "False",
    "Message_0_Condition_0_Logic": "Equal",
    "Message_0_Condition_0_Allow_Unset": "",
    "Message_1_Pages": "1",
    "Message_1_Conditions": "1",
    "Message_1_Condition_0_Type": "Flag_Bool",
    "Message_1_Condition_0_ID": "45701",
    "Message_1_Condition_0_Value": "True",
    "Message_1_Condition_0_Logic": "Equal",
    "Responses": "5",
    "Response_0_Messages": "1",
    "Response_0_Message_0": "0",
    "Response_1_Dialogue": "45716",
    "Response_1_Rewards": "1",
    "Response_1_Reward_0_Type": "Flag_Bool",
    "Response_1_Reward_0_ID": "45711",
    "Response_1_Reward_0_Value": "True",
    "Response_2_Dialogue": "45732",
    "Response_2_Vendor": "45733",
    "Response_2_Conditions": "1",
    "Response_2_Condition_0_Type": "Flag_Bool",
    "Response_2_Condition_0_ID": "45734",
    "Response_2_Condition_0_Value": "True",
    "Response_2_Condition_0_Logic": "Equal",
    "Response_3_Dialogue": "45735",
    "Response_3_Rewards": "1",
    "Response_3_Reward_0_Type": "Flag_Bool",
    "Response_3_Reward_0_ID": "45734",
    "Response_3_Reward_0_Value": "True",
    "Response_3_Conditions": "2",
    "Response_3_Condition_0_Type": "Quest",
    "Response_3_Condition_0_Logic": "Equal",
    "Response_3_Condition_0_ID": "45718",
    "Response_3_Condition_0_Status": "Completed",
    "Response_3_Condition_1_Type": "Flag_Bool",
    "Response_3_Condition_1_ID": "45734",
    "Response_3_Condition_1_Value": "False",
    "Response_3_Condition_1_Logic": "Equal",
    "Response_3_Condition_1_Allow_Unset": ""
  },
  "translation": {
    "Message_0_Page_0": "Hello, I'm <color=uncommon><name_npc></color>. I think <color=epic>Major Mac Alastair</color> would like to speak with you!",
    "Message_1_Page_0": "Hello <name_char>!",
    "Response_0": "Understood.",
    "Response_1": "What is your role?",
    "Response_2": "I'd like to trade.",
    "Response_3": "That's a lot of supplies you got there.",
    "Response_4": "Hello."
  }
}