{
  "name": "26782KDominicS3",
  "path": "Servers/DataSerializing/Workshop/Steam/content/304930/2483365750/Kuwait/Bundles/NPCs/M/3/Q/265 Concord/Dominic/26782KDominicS3/Asset.dat",
  "data": {
    "GUID": "2f421db42a8b444a9bc40e07dd39c9d7",
    "Type": "Quest",
    "ID": "26782",
    "Conditions": "1",
    "Condition_0_Type": "Item",
    "Condition_0_ID": "5786",
    "Condition_0_Amount": "2",
    "Condition_0_Reset": "",
    "Rewards": "3",
    "Reward_0_Type": "Currency",
    "Reward_0_Value": "100",
    "Reward_0_GUID": "b76b37b2d40c4054b850458e135408c6",
    "Reward_1_Type": "Reputation",
    "Reward_1_Value": "10",
    "Reward_2_Type": "Flag_Short_Random",
    "Reward_2_ID": "26765",
    "Reward_2_Min_Value": "0",
    "Reward_2_Max_Value": "4",
    "Reward_2_Modification": "Assign"
  },
  "translation": {
    "Name": "<color=#b8b188>Concord: </color><color=legendary>Fuel Source</color>",
    "Description": "<color=#FF69B4>Repeating Quest</color><br><color=epic>Major Dominic</color> needs you to get some machines to extract oil, so that they don't have to search the mainland."
  }
}