{
  "name": "FirstLove_03",
  "path": "Servers/DataSerializing/Workshop/Steam/content/304930/3000549606/Buak/Bundles/NPCs/Quests/Chapter_02/FirstLove_03/Asset.dat",
  "data": {
    "GUID": "3d65a3c3c08243a4a0f3039b529dfc9f",
    "Type": "Quest",
    "ID": "24568",
    "Conditions": "1",
    "Condition_0_Type": "Flag_Bool",
    "Condition_0_ID": "24567",
    "Condition_0_Value": "True",
    "Condition_0_Logic": "Equal",
    "Rewards": "2",
    "Reward_0_Type": "Experience",
    "Reward_0_Value": "50",
    "Reward_1_Type": "Reputation",
    "Reward_1_Value": "20"
  },
  "translation": {
    "Name": "First Love Part #4",
    "Description": "Retrieve a diamond from the safezone cellar.",
    "Condition_0": "Find {0}/1 Diamond"
  }
}