{
  "name": "PS_Dressing",
  "path": "Servers/DataSerializing/Workshop/Steam/content/304930/2683620106/Arid/Bundles/MAIN/Items/Medical/PS_Dressing/PS_Dressing.dat",
  "data": {
    "GUID": "59f7565930544fd4926c2a8952922b26",
    "Type": "Medical",
    "Rarity": "Epic",
    "Useable": "Consumeable",
    "ID": "59172",
    "Size_X": "1",
    "Size_Y": "1",
    "Size_Z": "0.32",
    "Aid": "",
    "Bleeding": "",
    "Health": "33",
    "Disinfectant": "3",
    "Equipable_Movement_Speed_Multiplier": "0.9"
  },
  "translation": {
    "Name": "Dressing",
    "Description": "<color=#21B427>+33 Health<br>+3 Immunity<br>Heals Bleeding</color>"
  }
}