{
  "name": "Survivor",
  "path": "Servers/DataSerializing/Workshop/Steam/content/304930/1497352180/Carpat/Bundles/CarpatLegacy/NPCs/Carpat_NPCS/Characters/Survivor/Asset.dat",
  "data": {
    "GUID": "5e9cbc042ca340919dc0688ff6a8343c",
    "Type": "NPC",
    "ID": "7200",
    "Hat": "426",
    "Shirt": "162",
    "Pants": "548",
    "Face": "1",
    "Hair": "1",
    "Beard": "1",
    "Color_Skin": "#F9E2AC",
    "Color_Hair": "#301A00",
    "Primary": "107",
    "Equipped": "Primary",
    "Dialogue": "7201"
  },
  "translation": {
    "Name": "Unknown Survivor",
    "Character": "<color=rare>Unknown Survivor</color>"
  }
}