{
  "name": "26254KLYaegerClaim",
  "path": "Servers/DataSerializing/Workshop/Steam/content/304930/2483365750/Kuwait/Bundles/NPCs/M/3/C/259 LSE/26250KLYaeger/26254KLYaegerClaim/Asset.dat",
  "data": {
    "GUID": "7e8230d9091d4b0dbc6b596fed67db34",
    "Type": "NPC",
    "ID": "26254",
    "Shirt": "5317",
    "Pants": "5322 ",
    "Face": "5",
    "Hair": "19",
    "Beard": "0",
    "Color_Skin": "#BEA582",
    "Color_Hair": "#191919",
    "Secondary": "5147",
    "Dialogue": "26280",
    "Conditions": "3",
    "Condition_0_Type": "Flag_Bool",
    "Condition_0_ID": "26515",
    "Condition_0_Value": "True",
    "Condition_0_Logic": "Equal",
    "Condition_1_Type": "Flag_Bool",
    "Condition_1_ID": "25050",
    "Condition_1_Value": "False",
    "Condition_1_Logic": "Equal",
    "Condition_1_Allow_Unset": "",
    "Condition_2_Type": "Time_Of_Day",
    "Condition_2_Second": "68400",
    "Condition_2_Logic": "Greater_Than_Or_Equal_To"
  },
  "translation": {
    "Name": "KuwaitNPCLiberatorLYaegerClaim",
    "Character": "<color=rare>Lieutenant Yaeger</color>"
  }
}