{
  "name": "Farmer_Georgette_Welcome",
  "path": "Servers/DataSerializing/Workshop/Steam/content/304930/1702240229/Greece/Bundles/NPCs/Dialogue/Farmer_Omega_Daughter/Farmer_Georgette_Welcome/Asset.dat",
  "data": {
    "GUID": "9d04d49cb0b549c4b25e4f86e5c7485d",
    "Type": "Dialogue",
    "ID": "3206",
    "Messages": "7",
    "Message_0_Pages": "1",
    "Message_0_Conditions": "1",
    "Message_0_Condition_0_Type": "Flag_Short",
    "Message_0_Condition_0_ID": "3017",
    "Message_0_Condition_0_Value": "-2",
    "Message_0_Condition_0_Logic": "Greater_Than",
    "Message_0_Condition_0_Allow_Unset": "",
    "Message_1_Pages": "1",
    "Message_1_Conditions": "3",
    "Message_1_Condition_0_Type": "Flag_Short",
    "Message_1_Condition_0_ID": "3017",
    "Message_1_Condition_0_Value": "-2",
    "Message_1_Condition_0_Logic": "Less_Than_Or_Equal_To",
    "Message_1_Condition_1_Type": "Flag_Short",
    "Message_1_Condition_1_ID": "3001",
    "Message_1_Condition_1_Value": "4",
    "Message_1_Condition_1_Logic": "Not_Equal",
    "Message_1_Condition_2_Type": "Flag_Short",
    "Message_1_Condition_2_ID": "3001",
    "Message_1_Condition_2_Value": "5",
    "Message_1_Condition_2_Logic": "Not_Equal",
    "Message_2_Pages": "1",
    "Message_2_Conditions": "4",
    "Message_2_Condition_0_Type": "Flag_Short",
    "Message_2_Condition_0_ID": "3017",
    "Message_2_Condition_0_Value": "-2",
    "Message_2_Condition_0_Logic": "Less_Than_Or_Equal_To",
    "Message_2_Condition_1_Type": "Flag_Short",
    "Message_2_Condition_1_ID": "3001",
    "Message_2_Condition_1_Value": "4",
    "Message_2_Condition_1_Logic": "Greater_Than_Or_Equal_To",
    "Message_2_Condition_2_Type": "Flag_Short",
    "Message_2_Condition_2_ID": "3001",
    "Message_2_Condition_2_Value": "5",
    "Message_2_Condition_2_Logic": "Less_Than_Or_Equal_To",
    "Message_2_Condition_3_Type": "Flag_Short",
    "Message_2_Condition_3_ID": "3207",
    "Message_2_Condition_3_Value": "0",
    "Message_2_Condition_3_Logic": "Equal",
    "Message_2_Condition_3_Allow_Unset": "",
    "Message_3_Pages": "1",
    "Message_3_Conditions": "4",
    "Message_3_Condition_0_Type": "Flag_Short",
    "Message_3_Condition_0_ID": "3017",
    "Message_3_Condition_0_Value": "-2",
    "Message_3_Condition_0_Logic": "Less_Than_Or_Equal_To",
    "Message_3_Condition_1_Type": "Flag_Short",
    "Message_3_Condition_1_ID": "3001",
    "Message_3_Condition_1_Value": "4",
    "Message_3_Condition_1_Logic": "Greater_Than_Or_Equal_To",
    "Message_3_Condition_2_Type": "Flag_Short",
    "Message_3_Condition_2_ID": "3001",
    "Message_3_Condition_2_Value": "5",
    "Message_3_Condition_2_Logic": "Less_Than_Or_Equal_To",
    "Message_3_Condition_3_Type": "Flag_Short",
    "Message_3_Condition_3_ID": "3207",
    "Message_3_Condition_3_Value": "1",
    "Message_3_Condition_3_Logic": "Equal",
    "Message_4_Pages": "1",
    "Message_4_Conditions": "4",
    "Message_4_Condition_0_Type": "Flag_Short",
    "Message_4_Condition_0_ID": "3017",
    "Message_4_Condition_0_Value": "-2",
    "Message_4_Condition_0_Logic": "Less_Than_Or_Equal_To",
    "Message_4_Condition_1_Type": "Flag_Short",
    "Message_4_Condition_1_ID": "3001",
    "Message_4_Condition_1_Value": "4",
    "Message_4_Condition_1_Logic": "Greater_Than_Or_Equal_To",
    "Message_4_Condition_2_Type": "Flag_Short",
    "Message_4_Condition_2_ID": "3001",
    "Message_4_Condition_2_Value": "5",
    "Message_4_Condition_2_Logic": "Less_Than_Or_Equal_To",
    "Message_4_Condition_3_Type": "Flag_Short",
    "Message_4_Condition_3_ID": "3207",
    "Message_4_Condition_3_Value": "2",
    "Message_4_Condition_3_Logic": "Equal",
    "Message_5_Pages": "1",
    "Message_5_Conditions": "4",
    "Message_5_Condition_0_Type": "Flag_Short",
    "Message_5_Condition_0_ID": "3017",
    "Message_5_Condition_0_Value": "-2",
    "Message_5_Condition_0_Logic": "Less_Than_Or_Equal_To",
    "Message_5_Condition_1_Type": "Flag_Short",
    "Message_5_Condition_1_ID": "3001",
    "Message_5_Condition_1_Value": "4",
    "Message_5_Condition_1_Logic": "Greater_Than_Or_Equal_To",
    "Message_5_Condition_2_Type": "Flag_Short",
    "Message_5_Condition_2_ID": "3001",
    "Message_5_Condition_2_Value": "5",
    "Message_5_Condition_2_Logic": "Less_Than_Or_Equal_To",
    "Message_5_Condition_3_Type": "Flag_Short",
    "Message_5_Condition_3_ID": "3207",
    "Message_5_Condition_3_Value": "3",
    "Message_5_Condition_3_Logic": "Equal",
    "Message_6_Pages": "1",
    "Message_6_Conditions": "4",
    "Message_6_Condition_0_Type": "Flag_Short",
    "Message_6_Condition_0_ID": "3017",
    "Message_6_Condition_0_Value": "-2",
    "Message_6_Condition_0_Logic": "Less_Than_Or_Equal_To",
    "Message_6_Condition_1_Type": "Flag_Short",
    "Message_6_Condition_1_ID": "3001",
    "Message_6_Condition_1_Value": "4",
    "Message_6_Condition_1_Logic": "Greater_Than_Or_Equal_To",
    "Message_6_Condition_2_Type": "Flag_Short",
    "Message_6_Condition_2_ID": "3001",
    "Message_6_Condition_2_Value": "5",
    "Message_6_Condition_2_Logic": "Less_Than_Or_Equal_To",
    "Message_6_Condition_3_Type": "Flag_Short",
    "Message_6_Condition_3_ID": "3207",
    "Message_6_Condition_3_Value": "-1",
    "Message_6_Condition_3_Logic": "Equal",
    "Responses": "10",
    "Response_0_Messages": "1",
    "Response_0_Message_0": "2",
    "Response_1_Messages": "1",
    "Response_1_Message_0": "2",
    "Response_1_Dialogue": "3208",
    "Response_2_Messages": "1",
    "Response_2_Message_0": "3",
    "Response_2_Dialogue": "3209",
    "Response_3_Messages": "1",
    "Response_3_Message_0": "3",
    "Response_4_Messages": "1",
    "Response_4_Message_0": "4",
    "Response_4_Dialogue": "3211",
    "Response_4_Quest": "3212",
    "Response_4_Conditions": "1",
    "Response_4_Condition_0_Type": "Quest",
    "Response_4_Condition_0_Logic": "Equal",
    "Response_4_Condition_0_ID": "3212",
    "Response_4_Condition_0_Status": "Ready",
    "Response_4_Condition_0_Reset": "",
    "Response_5_Messages": "1",
    "Response_5_Message_0": "4",
    "Response_6_Messages": "1",
    "Response_6_Message_0": "5",
    "Response_7_Messages": "1",
    "Response_7_Message_0": "6",
    "Response_8_Messages": "1",
    "Response_8_Message_0": "1",
    "Response_9_Messages": "1",
    "Response_9_Message_0": "0"
  },
  "translation": {
    "Message_0_Page_0": "Do I know you?",
    "Message_1_Page_0": "...Uh, Hey! Welcome to the Greenhouse... nothing to see here.",
    "Message_2_Page_0": "<i>She quickly puts something behind her back</i> He...Hello! How're you doing <name_char>?",
    "Message_3_Page_0": "Look, please don't tell my father. Please! I have a good reason.",
    "Message_4_Page_0": "*She glances around quickly* Did you get the, uh, supplies?",
    "Message_5_Page_0": "Hiya <name_char>! Thank you so much for all your help, I owe you one.",
    "Message_6_Page_0": "Come on man! Why'd you have to tell him! I thought you'd understand, clearly I was wrong.",
    "Response_0": "Hey <name_npc>, I'm doing well.",
    "Response_1": "Whatcha got there?",
    "Response_2": "Whatcha got there?",
    "Response_3": "Goodbye.",
    "Response_4": "Hey <name_npc>, I got you those, supplies.",
    "Response_5": "I'm still working on that!",
    "Response_6": "Hey <name_npc>! I was happy to help.",
    "Response_7": "You were stealing! It was the right thing to do.",
    "Response_8": "Hmm... I don't know, there are lot of plants to look at.",
    "Response_9": "Probably not."
  }
}