{
  "name": "PS_Empty_Spray_Can",
  "path": "Servers/DataSerializing/Workshop/Steam/content/304930/2683620106/Arid/Bundles/MAIN/Items/Supplies/PS_Empty_Spray_Can/PS_Empty_Spray_Can.dat",
  "data": {
    "GUID": "d51d9c2684ce42c99bfd12fd7bae36cc",
    "Type": "Supply",
    "Rarity": "Common",
    "ID": "59626",
    "Size_X": "1",
    "Size_Y": "2",
    "Size_Z": "0.58",
    "Blueprints": "1",
    "Blueprint_0_Type": "Gear",
    "Blueprint_0_Supplies": "1",
    "Blueprint_0_Supply_0_ID": "59626",
    "Blueprint_0_Product": "59000",
    "Blueprint_0_Products": "2",
    "Blueprint_0_Tool": "59004",
    "Blueprint_0_Build": "27"
  },
  "translation": {
    "Name": "Empty Spray Can",
    "Description": "Metal can used for aerosol paint.<br><br><color=#FFC000>Nomad's Exchange Item</color>"
  }
}