[
  {
    "type": 0,
    "point": {
      "x": 527.9617,
      "y": 58.97908,
      "z": 592.069946
    }
  },
  {
    "type": 0,
    "point": {
      "x": 861.7012,
      "y": 71.81206,
      "z": 834.0116
    }
  },
  {
    "type": 0,
    "point": {
      "x": -593.698669,
      "y": 39.2660446,
      "z": 868.078857
    }
  },
  {
    "type": 0,
    "point": {
      "x": -669.580933,
      "y": 74.0665741,
      "z": 218.8468
    }
  },
  {
    "type": 0,
    "point": {
      "x": -900.649353,
      "y": 77.28775,
      "z": -345.900024
    }
  },
  {
    "type": 0,
    "point": {
      "x": -588.231567,
      "y": 39.54839,
      "z": 871.519043
    }
  },
  {
    "type": 0,
    "point": {
      "x": -588.367554,
      "y": 38.7246361,
      "z": 865.5294
    }
  },
  {
    "type": 0,
    "point": {
      "x": -582.5154,
      "y": 38.8463669,
      "z": 868.7147
    }
  },
  {
    "type": 0,
    "point": {
      "x": -588.5939,
      "y": 38.391,
      "z": 860.520752
    }
  },
  {
    "type": 0,
    "point": {
      "x": -795.0318,
      "y": 38.40078,
      "z": 603.0526
    }
  },
  {
    "type": 0,
    "point": {
      "x": -802.0676,
      "y": 38.40078,
      "z": 605.1483
    }
  },
  {
    "type": 0,
    "point": {
      "x": -799.099365,
      "y": 38.40078,
      "z": 609.852661
    }
  },
  {
    "type": 0,
    "point": {
      "x": -792.439331,
      "y": 38.40078,
      "z": 608.3871
    }
  },
  {
    "type": 0,
    "point": {
      "x": -673.295532,
      "y": 75.52737,
      "z": 223.362427
    }
  },
  {
    "type": 0,
    "point": {
      "x": -675.357666,
      "y": 75.065155,
      "z": 218.113647
    }
  },
  {
    "type": 0,
    "point": {
      "x": -670.5802,
      "y": 75.56476,
      "z": 213.788452
    }
  },
  {
    "type": 0,
    "point": {
      "x": -665.068,
      "y": 74.5104446,
      "z": 220.706787
    }
  },
  {
    "type": 0,
    "point": {
      "x": -902.0112,
      "y": 77.65367,
      "z": -341.021
    }
  },
  {
    "type": 0,
    "point": {
      "x": -896.2554,
      "y": 76.51261,
      "z": -343.022034
    }
  },
  {
    "type": 0,
    "point": {
      "x": -901.459351,
      "y": 77.7081451,
      "z": -351.319458
    }
  },
  {
    "type": 0,
    "point": {
      "x": -906.6433,
      "y": 78.82686,
      "z": -349.7121
    }
  },
  {
    "type": 0,
    "point": {
      "x": 87.73938,
      "y": 69.83394,
      "z": -644.89624
    }
  },
  {
    "type": 0,
    "point": {
      "x": 83.62805,
      "y": 69.6422043,
      "z": -641.3644
    }
  },
  {
    "type": 0,
    "point": {
      "x": 82.4032,
      "y": 68.81954,
      "z": -647.0408
    }
  },
  {
    "type": 0,
    "point": {
      "x": 93.2785645,
      "y": 70.4454651,
      "z": -643.812744
    }
  },
  {
    "type": 0,
    "point": {
      "x": 92.5802,
      "y": 69.62181,
      "z": -648.8816
    }
  },
  {
    "type": 0,
    "point": {
      "x": 465.3108,
      "y": 66.59284,
      "z": -650.931335
    }
  },
  {
    "type": 0,
    "point": {
      "x": 468.438477,
      "y": 67.45911,
      "z": -646.6931
    }
  },
  {
    "type": 0,
    "point": {
      "x": 471.7765,
      "y": 67.30369,
      "z": -652.4321
    }
  },
  {
    "type": 0,
    "point": {
      "x": 462.678223,
      "y": 66.35037,
      "z": -645.908447
    }
  },
  {
    "type": 0,
    "point": {
      "x": 462.562866,
      "y": 65.68098,
      "z": -655.642
    }
  },
  {
    "type": 0,
    "point": {
      "x": 450.117065,
      "y": 48.3413162,
      "z": -213.849426
    }
  },
  {
    "type": 0,
    "point": {
      "x": 455.429565,
      "y": 48.9203,
      "z": -211.6463
    }
  },
  {
    "type": 0,
    "point": {
      "x": 454.912,
      "y": 49.1376038,
      "z": -216.657349
    }
  },
  {
    "type": 0,
    "point": {
      "x": 459.775635,
      "y": 48.86454,
      "z": -218.41864
    }
  },
  {
    "type": 0,
    "point": {
      "x": 450.542847,
      "y": 48.7832031,
      "z": -208.160217
    }
  },
  {
    "type": 0,
    "point": {
      "x": 567.344,
      "y": 58.49245,
      "z": 320.2898
    }
  },
  {
    "type": 0,
    "point": {
      "x": 565.487061,
      "y": 59.3574448,
      "z": 313.626343
    }
  },
  {
    "type": 0,
    "point": {
      "x": 572.6837,
      "y": 58.9179764,
      "z": 315.86792
    }
  },
  {
    "type": 0,
    "point": {
      "x": 572.5957,
      "y": 57.9190063,
      "z": 323.3855
    }
  },
  {
    "type": 0,
    "point": {
      "x": 577.9398,
      "y": 57.8759842,
      "z": 320.733643
    }
  },
  {
    "type": 0,
    "point": {
      "x": 866.447144,
      "y": 72.11894,
      "z": 830.8074
    }
  },
  {
    "type": 0,
    "point": {
      "x": 862.0083,
      "y": 70.56103,
      "z": 829.506
    }
  },
  {
    "type": 0,
    "point": {
      "x": 854.194336,
      "y": 69.66251,
      "z": 832.301636
    }
  },
  {
    "type": 0,
    "point": {
      "x": 868.9005,
      "y": 71.21768,
      "z": 826.281
    }
  },
  {
    "type": 0,
    "point": {
      "x": 531.8085,
      "y": 59.3687859,
      "z": 596.7894
    }
  },
  {
    "type": 0,
    "point": {
      "x": 526.284058,
      "y": 57.679615,
      "z": 596.4678
    }
  },
  {
    "type": 0,
    "point": {
      "x": 530.4453,
      "y": 57.747818,
      "z": 602.8273
    }
  },
  {
    "type": 0,
    "point": {
      "x": 535.0725,
      "y": 58.54057,
      "z": 605.6345
    }
  },
  {
    "type": 0,
    "point": {
      "x": -69.61963,
      "y": 56.09194,
      "z": 561.1406
    }
  },
  {
    "type": 0,
    "point": {
      "x": -64.18738,
      "y": 56.4775467,
      "z": 563.1422
    }
  },
  {
    "type": 0,
    "point": {
      "x": -68.38922,
      "y": 56.2058754,
      "z": 567.1017
    }
  },
  {
    "type": 0,
    "point": {
      "x": -62.9187,
      "y": 56.3274231,
      "z": 567.8672
    }
  },
  {
    "type": 0,
    "point": {
      "x": -74.65588,
      "y": 55.71855,
      "z": 564.1461
    }
  },
  {
    "type": 0,
    "point": {
      "x": 825.6095,
      "y": 70.38216,
      "z": -75.6814
    }
  },
  {
    "type": 0,
    "point": {
      "x": 830.2141,
      "y": 69.78169,
      "z": -79.10376
    }
  },
  {
    "type": 0,
    "point": {
      "x": 825.000244,
      "y": 69.717926,
      "z": -81.24567
    }
  },
  {
    "type": 0,
    "point": {
      "x": 830.5016,
      "y": 70.9870148,
      "z": -72.74628
    }
  },
  {
    "type": 0,
    "point": {
      "x": 834.9386,
      "y": 68.7215042,
      "z": -82.7608
    }
  }
]